setup.py
gitpm/__init__.py
gitpm.egg-info/PKG-INFO
gitpm.egg-info/SOURCES.txt
gitpm.egg-info/dependency_links.txt
gitpm.egg-info/entry_points.txt
gitpm.egg-info/not-zip-safe
gitpm.egg-info/requires.txt
gitpm.egg-info/top_level.txt
gitpm/core/__init__.py
gitpm/core/project.py
gitpm/tools/__init__.py
gitpm/tools/gitpm.py
gitpm/tools/gp_clone.py
gitpm/tools/gp_create.py
gitpm/tools/gp_details.py
gitpm/tools/gp_git.py
gitpm/tools/gp_list.py
gitpm/tools/gp_loop.py
gitpm/tools/gp_remove.py
gitpm/tools/gp_set.py
gitpm/tools/gp_stat.py
gitpm/tools/gp_sync.py
gitpm/tools/gp_update.py