Metadata-Version: 1.1
Name: gitpm
Version: 0.7.0
Summary: Efficient code-base management based on git.
Home-page: http://github.com/finnmglas/gitPM
Author: Finn M Glas
Author-email: finn@finnmglas.com
License: MIT
Keywords: git management repositories manager efficiency
Platform: UNKNOWN
Classifier: Development Status :: 3 - Alpha
Classifier: Environment :: Console
Classifier: License :: OSI Approved :: MIT License
Classifier: Programming Language :: Python :: 3.5
Classifier: Programming Language :: Python :: 3.6
Classifier: Programming Language :: Python :: 3.7
Classifier: Programming Language :: Python :: 3.8
Classifier: Programming Language :: Python :: 3.9
Classifier: Intended Audience :: Information Technology
Classifier: Intended Audience :: Developers
Classifier: Topic :: Software Development
Classifier: Topic :: Software Development :: Version Control
Classifier: Topic :: Software Development :: Version Control :: Git
